yamp/__init__.py
yamp/plugin.py
yamp/repo_item.py
mkdocs_yamp-0.1.2.dist-info/METADATA
mkdocs_yamp-0.1.2.dist-info/WHEEL
mkdocs_yamp-0.1.2.dist-info/entry_points.txt
mkdocs_yamp-0.1.2.dist-info/licenses/LICENSE
mkdocs_yamp-0.1.2.dist-info/RECORD
