Metadata-Version: 2.1
Name: mkdocs-yamp
Version: 0.1.2
Summary: Yet Another Multirepo Plugin for MkDocs. Adds additional repositories to a directory within the docs directory to be referenced in the navigation
Project-URL: Homepage, https://github.com/boozallen/mkdocs-yamp-plugin
Author-email: Steven Terrana <steventerrana@gmail.com>
License-File: LICENSE
Keywords: mkdocs
Classifier: Intended Audience :: Developers
Classifier: License :: OSI Approved :: Apache Software License
Classifier: Programming Language :: Python
Classifier: Programming Language :: Python :: 3 :: Only
Classifier: Programming Language :: Python :: 3.4
Classifier: Programming Language :: Python :: 3.5
Classifier: Programming Language :: Python :: 3.6
Classifier: Programming Language :: Python :: 3.7
Requires-Python: >=2.7
Requires-Dist: gitpython>=3.1.27
Requires-Dist: mkdocs>=1.0.4
